MANIFEST.in
README.rst
setup.py
Carcade.egg-info/PKG-INFO
Carcade.egg-info/SOURCES.txt
Carcade.egg-info/dependency_links.txt
Carcade.egg-info/entry_points.txt
Carcade.egg-info/requires.txt
Carcade.egg-info/top_level.txt
carcade/__init__.py
carcade/cli.py
carcade/conf.py
carcade/core.py
carcade/environments.py
carcade/exceptions.py
carcade/global_settings.py
carcade/i18n.py
carcade/server.py
carcade/utils.py
carcade/template/layouts/.gitkeep
carcade/template/pages/.gitkeep
carcade/template/static/.gitkeep
carcade/template/translations/.gitkeep
tests/__init__.py
tests/__init__.pyc
tests/create_tree_test.pyc
tests/environments_test.pyc
tests/environments_tests.py
tests/environments_tests.pyc
tests/i18n_tests.py
tests/i18n_tests.pyc
tests/tree_manipulations_tests.py
tests/tree_manipulations_tests.pyc
tests/fixtures/ru.po
tests/fixtures/bundle/one.css
tests/fixtures/bundle/two.css
tests/fixtures/fixture/a/1/hello/.gitkeep
tests/fixtures/fixture/a/2/.gitkeep
tests/fixtures/fixture/b/.gitkeep
tests/fixtures/fixture/c/.gitkeep
tests/fixtures/fixture2/blog/a/.gitkeep
tests/fixtures/fixture2/blog/b/.gitkeep
tests/fixtures/fixture2/blog/c/.gitkeep
tests/fixtures/fixture2/blog/d/.gitkeep
tests/fixtures/fixture2/blog/e/.gitkeep
tests/fixtures/fixture2/blog/f/.gitkeep
tests/fixtures/fixture2/blog/g/.gitkeep
tests/fixtures/layouts/test.html