Metadata-Version: 1.1
Name: Carcade
Version: 0.1
Summary: Static site generator powered by Jinja2.
Home-page: https://github.com/aromanovich/carcade
Author: Anton Romanovich
Author-email: anthony.romanovich@gmail.com
License: BSD
Platform: UNKNOWN
Classifier: Development Status :: 4 - Beta
Classifier: License :: OSI Approved :: BSD License
Classifier: Environment :: Console
Classifier: Intended Audience :: Developers
Classifier: Intended Audience :: Information Technology
Classifier: Programming Language :: Python
Classifier: Programming Language :: Python :: 2
Classifier: Programming Language :: Python :: 2.6
Classifier: Programming Language :: Python :: 2.7
Classifier: Topic :: Software Development
Classifier: Topic :: Software Development :: Build Tools
Classifier: Topic :: Software Development :: Code Generators
Classifier: Topic :: Internet :: WWW/HTTP :: Site Management
Classifier: Operating System :: POSIX
Classifier: Operating System :: Unix
